[
  {
    "name" : "Arian Foster",
    "email" : "arian.foster@arcu.com",
    "number" : "27",
    "password" : "33|&u%i7ToTqY9V"
  },
  {
    "name" : "Otto I the Great, Holy Roman Emperor",
    "email" : "otto_i_the_great_holy_roman_emperor@amet.com",
    "number" : "60",
    "password" : ";fB5RZ7yR}9:k5v"
  },
  {
    "name" : "Gal Gadot",
    "email" : "galgadot@sed.com",
    "number" : "50",
    "password" : "X05S&6j[JwhsW:4"
  },
  {
    "name" : "William the Conqueror",
    "email" : "william.the.conqueror@sodales.com",
    "number" : "87",
    "password" : "U39*Eh@g8K%Ct9r"
  },
  {
    "name" : "Vladimir Putin",
    "email" : "vladimirputin@convallis.com",
    "number" : "84",
    "password" : "Bw?tp9Em*UB237@"
  },
  {
    "name" : "Elizabeth Banks",
    "email" : "elizabeth_banks@pellentesque.com",
    "number" : "25",
    "password" : "HrLH7#5_t0T_2dk"
  },
  {
    "name" : "Jim Parsons",
    "email" : "jimparsons@tellus.com",
    "number" : "47",
    "password" : "jh91;0V1GSvOq##"
  },
  {
    "name" : "Maiara Walsh",
    "email" : "maiara.walsh@feugiat.com",
    "number" : "22",
    "password" : "Ev6R]666&YVmd#o"
  },
  {
    "name" : "Jensen Ackles",
    "email" : "jensen_ackles@bibendum.com",
    "number" : "50",
    "password" : "ji)2N@DR$4nZ8s4"
  },
  {
    "name" : "Hannibal",
    "email" : "hannibal@est.com",
    "number" : "72",
    "password" : "hoc83O4SS9++Xe%"
  },
  {
    "name" : "Gareth Edwards",
    "email" : "gareth.edwards@nulla.com",
    "number" : "76",
    "password" : "B&i33KqR$J9|m2f"
  },
  {
    "name" : "Jessica Chastain",
    "email" : "jessica_chastain@amet.com",
    "number" : "20",
    "password" : "EDe]L18s6S|bs+3"
  },
  {
    "name" : "Simon Bolivar Buckner",
    "email" : "simon_bolivar_buckner@donec.com",
    "number" : "37",
    "password" : "CyD4_6/SY8m[6kl"
  },
  {
    "name" : "Charles V, Holy Roman Emperor",
    "email" : "charlesvholyromanemperor@congue.com",
    "number" : "69",
    "password" : "wg0R0[HK4+:4Wey"
  },
  {
    "name" : "Analeigh Tipton",
    "email" : "analeightipton@volutpat.com",
    "number" : "99",
    "password" : "pBb,83_YfU=V08b"
  },
  {
    "name" : "Diane Lane",
    "email" : "dianelane@commodo.com",
    "number" : "62",
    "password" : "R&u60)2bN*qK6Qo"
  },
  {
    "name" : "Taylor Momsen",
    "email" : "taylor.momsen@feugiat.com",
    "number" : "94",
    "password" : "E7t9jJ}s9X6hV-:"
  },
  {
    "name" : "Heath Ledger",
    "email" : "heath_ledger@bibendum.com",
    "number" : "23",
    "password" : "h|6q5*MDm/D6wH3"
  },
  {
    "name" : "Emily Bett Rickards",
    "email" : "emily_bett_rickards@magna.com",
    "number" : "77",
    "password" : "4@eN{FZk1@58nZl"
  },
  {
    "name" : "Benjamin Franklin",
    "email" : "benjamin.franklin@arcu.com",
    "number" : "66",
    "password" : "}kCuNMc(63Bk89|"
  }
]